pgxsq.py
pgxsq-0.2.0.dist-info/LICENSE
pgxsq-0.2.0.dist-info/METADATA
pgxsq-0.2.0.dist-info/WHEEL
pgxsq-0.2.0.dist-info/entry_points.txt
pgxsq-0.2.0.dist-info/top_level.txt
pgxsq-0.2.0.dist-info/RECORD
