Metadata-Version: 2.1
Name: pgxsq
Version: 0.2.0
Summary: Write Postgres extensions as Sqitch projects.
Author-email: Erik Wienhold <ewie@ewie.name>
License: BSD-3-Clause
Project-URL: Repository, https://git.sr.ht/~ewie/pgxsq
Classifier: Intended Audience :: Developers
Classifier: License :: OSI Approved :: BSD License
Classifier: Programming Language :: Python :: 3 :: Only
Classifier: Programming Language :: Python :: 3
Classifier: Programming Language :: Python :: 3.8
Classifier: Programming Language :: Python :: 3.9
Classifier: Programming Language :: Python :: 3.10
Classifier: Programming Language :: Python :: 3.11
Classifier: Topic :: Software Development :: Build Tools
Requires-Python: >=3.8
License-File: LICENSE
